delta_method/__init__.py
delta_method-0.1.dist-info/LICENSE
delta_method-0.1.dist-info/METADATA
delta_method-0.1.dist-info/WHEEL
delta_method-0.1.dist-info/top_level.txt
delta_method-0.1.dist-info/RECORD
